LICENSE.txt
MANIFEST.in
README.md
classifiers.txt
requirements.txt
setup.cfg
setup.py
pydigree/__init__.py
pydigree/common.py
pydigree/exceptions.py
pydigree/ibs.py
pydigree/individual.py
pydigree/individualcontainer.py
pydigree/paths.py
pydigree/pedigree.py
pydigree/pedigreecollection.py
pydigree/phenotypes.py
pydigree/population.py
pydigree/rand.py
pydigree/recombination.py
pydigree.egg-info/PKG-INFO
pydigree.egg-info/SOURCES.txt
pydigree.egg-info/dependency_links.txt
pydigree.egg-info/top_level.txt
pydigree/cydigree/__init__.py
pydigree/cydigree/cyfuncs.c
pydigree/cydigree/cyfuncs.pyx
pydigree/cydigree/datastructures.c
pydigree/cydigree/datastructures.pyx
pydigree/cydigree/sparray2.c
pydigree/cydigree/sparray2.cpp
pydigree/cydigree/sparsearray.cpp
pydigree/cydigree/sparsearray.pyx
pydigree/cydigree/sparsearray2.cpp
pydigree/cydigree/varianttree.c
pydigree/cydigree/vcfparse.c
pydigree/cydigree/vcfparse.pyx
pydigree/datastructures/__init__.py
pydigree/genotypes/__init__.py
pydigree/genotypes/alleles.py
pydigree/genotypes/chromosometemplate.py
pydigree/genotypes/genoabc.py
pydigree/genotypes/genotypecontainers.py
pydigree/genotypes/labelledalleles.py
pydigree/genotypes/sparsealleles.py
pydigree/io/__init__.py
pydigree/io/base.py
pydigree/io/beagle.py
pydigree/io/genomesimla.py
pydigree/io/kinship.py
pydigree/io/plink.py
pydigree/io/sgs.py
pydigree/io/smartopen.py
pydigree/io/vcf.py
pydigree/sgs/__init__.py
pydigree/sgs/sgs.py
pydigree/simulation/__init__.py
pydigree/simulation/chromosomepool.py
pydigree/simulation/mating.py
pydigree/simulation/trait.py
pydigree/simulation/genedrop/__init__.py
pydigree/simulation/genedrop/constrained_mendelian.py
pydigree/simulation/genedrop/naivegenedrop.py
pydigree/simulation/genedrop/simulation.py
pydigree/stats/__init__.py
pydigree/stats/mathfuncs.py
pydigree/stats/stattests.py
pydigree/stats/variancecomponents.py
pydigree/stats/mixedmodel/__init__.py
pydigree/stats/mixedmodel/likelihood.py
pydigree/stats/mixedmodel/maximization.py
pydigree/stats/mixedmodel/mixedmodel.py
pydigree/stats/mixedmodel/mixin.py
sample_pedigrees/charlesii.ped
